naylence/fame/security/cert/attachment_cert_validator.py
naylence/fame/security/cert/attachment_cert_validator_factory.py
naylence/fame/security/cert/ca_fastapi_router.py
naylence/fame/security/cert/ca_server.py
naylence/fame/security/cert/ca_service.py
naylence/fame/security/cert/ca_service_client.py
naylence/fame/security/cert/ca_service_factory.py
naylence/fame/security/cert/certificate_cache.py
naylence/fame/security/cert/certificate_manager.py
naylence/fame/security/cert/certificate_signing_service_factory.py
naylence/fame/security/cert/default_ca_service.py
naylence/fame/security/cert/default_ca_service_factory.py
naylence/fame/security/cert/default_certificate_manager.py
naylence/fame/security/cert/default_certificate_manager_factory.py
naylence/fame/security/cert/fastapi_model.py
naylence/fame/security/cert/grants.py
naylence/fame/security/cert/internal_ca_service.py
naylence/fame/security/cert/setup_pki.py
naylence/fame/security/cert/util.py
naylence/fame/security/encryption/channel/__init__.py
naylence/fame/security/encryption/channel/channel_encryption_manager.py
naylence/fame/security/encryption/channel/channel_encryption_manager_factory.py
naylence/fame/security/encryption/composite_encryption_manager.py
naylence/fame/security/encryption/composite_encryption_manager_factory.py
naylence/fame/security/encryption/default_secure_channel_manager.py
naylence/fame/security/encryption/default_secure_channel_manager_factory.py
naylence/fame/security/encryption/encryption_manager_registry.py
naylence/fame/security/encryption/sealed/__init__.py
naylence/fame/security/encryption/sealed/x25519_encryption_manager.py
naylence/fame/security/encryption/sealed/x25519_encryption_manager_factory.py
naylence/fame/security/keys/x5c_key_manager.py
naylence/fame/security/keys/x5c_key_manager_factory.py
naylence/fame/stickiness/aft_helper.py
naylence/fame/stickiness/aft_load_balancer_stickiness_manager.py
naylence/fame/stickiness/aft_load_balancer_stickiness_manager_factory.py
naylence_advanced_security-0.3.1.dist-info/METADATA
naylence_advanced_security-0.3.1.dist-info/WHEEL
naylence_advanced_security-0.3.1.dist-info/entry_points.txt
naylence_advanced_security-0.3.1.dist-info/licenses/LICENSE
naylence_advanced_security-0.3.1.dist-info/RECORD
