Metadata-Version: 2.4
Name: naylence-advanced-security
Version: 0.3.1
Summary: Naylence Advanced Security
License: BSL
License-File: LICENSE
Author: naylencedev@gmail.com
Requires-Python: >=3.12
Classifier: License :: Other/Proprietary License
Classifier: Programming Language :: Python :: 3
Classifier: Programming Language :: Python :: 3.12
Classifier: Programming Language :: Python :: 3.13
Classifier: Programming Language :: Python :: 3.14
Requires-Dist: cryptography (>=45.0.2,<46.0.0)
Requires-Dist: naylence-runtime (>=0.3.8,<0.4.0)
Requires-Dist: pyjwt (>=2.10.1,<3.0.0)
